CommenlyzerEngine/__init__.py
CommenlyzerEngine/classifier.py
CommenlyzerEngine/entities.py
CommenlyzerEngine/summarization.py
CommenlyzerEngine-1.0.1.dist-info/LICENSE
CommenlyzerEngine-1.0.1.dist-info/METADATA
CommenlyzerEngine-1.0.1.dist-info/WHEEL
CommenlyzerEngine-1.0.1.dist-info/top_level.txt
CommenlyzerEngine-1.0.1.dist-info/RECORD
