Metadata-Version: 2.1
Name: CommenlyzerEngine
Version: 1.0.1
Summary: UNKNOWN
Home-page: https://github.com/fsadannn/CommenlyzerEngine
Author: Frank Sadan Naranjo Noda, Hian Cañizares Días
Author-email: fsadannn@gmail.com, hiancdtrsnm@gmail.com
License: MIT
Download-URL: https://github.com/fsadannn/CommenlyzerEngine/tarball/1.0.1
Platform: UNKNOWN
Classifier: Development Status :: 5 - Production/Stable
Classifier: License :: OSI Approved :: MIT License
Classifier: Programming Language :: Python :: 3.6
Classifier: Topic :: Software Development :: Libraries :: Python Modules
Requires-Dist: toml
Requires-Dist: sklearn
Requires-Dist: joblib
Requires-Dist: spacy
Requires-Dist: gensim
